mangas_dl/__init__.py
mangas_dl/__main__.py
mangas_dl/download_chapters_functions.py
mangas_dl/mangas_dl_class.py
mangas_dl/pre_download_functions.py
mangas_dl/Headers/__init__.py
mangas_dl/Headers/download_and_convert.py
mangas_dl/Headers/errors.py
mangas_dl/Headers/functions.py
mangas_dl/Headers/functions_formatting.py
mangas_dl/Headers/functions_os.py
mangas_dl/Headers/functions_web.py
mangas_dl-1.0.2.data/data/mangas_dl/HELP.md
mangas_dl-1.0.2.data/data/mangas_dl/conf.ini
mangas_dl-1.0.2.data/data/mangas_dl/language_codes.json
mangas_dl-1.0.2.data/data/mangas_dl/settings.json
mangas_dl-1.0.2.data/data/mangas_dl/websites_used.json
mangas_dl-1.0.2.dist-info/LICENSE
mangas_dl-1.0.2.dist-info/METADATA
mangas_dl-1.0.2.dist-info/WHEEL
mangas_dl-1.0.2.dist-info/entry_points.txt
mangas_dl-1.0.2.dist-info/top_level.txt
mangas_dl-1.0.2.dist-info/RECORD
