Metadata-Version: 2.1
Name: mangas-dl
Version: 1.0.2
Summary: Mangas' scans downloader app
Home-page: https://github.com/Boubou0909/Mangas-dl
Author: Boubou0909
Author-email: balthazar0909@gmail.com
License: UNKNOWN
Platform: UNKNOWN
Classifier: Programming Language :: Python :: 3.9
License-File: LICENSE
Requires-Dist: requests-HTML (>=0.10.0)
Requires-Dist: MangaDex.py (>=2.0.6)
Requires-Dist: pillow (>=8.0.1)
Requires-Dist: imgurpython (>=1.1.7)
